{
  "name": "Huberman Lab",
  "slug": "huberman-lab",
  "tagline": "Science-based tools for everyday life from a Stanford neuroscientist",
  "description": "The Huberman Lab podcast, hosted by Dr. Andrew Huberman, a Stanford School of Medicine neuroscientist, translates complex research into actionable protocols for mental and physical health. It provides science-based explanations and direct tools for improving sleep, focus, stress management, learning, and physical performance. Each episode deeply explores a single topic, breaking down the underlying biology—such as the role of dopamine or neural plasticity—and offers specific, step-by-step recommendations for implementation.\n\nKey features include its rigorous adherence to peer-reviewed science, the provision of multi-tool protocols that combine behavioral, nutritional, and supplementation strategies, and detailed episode timestamps for easy navigation to sections of immediate interest. This podcast is for anyone seeking to understand the \"why\" behind health advice, including students, professionals, athletes, and individuals looking to make informed, long-term changes to their well-being.\n\nThe main benefit is gaining a foundational understanding of your own nervous system, empowering you to tailor and adjust routines based on evidence rather than trends. For example, a listener struggling with inconsistent sleep could learn not only the science of circadian rhythms but also receive a concrete protocol involving morning sunlight viewing, temperature regulation, and caffeine timing, enabling them to systematically improve their sleep quality.",
  "category": "Health",
  "host": "Dr. Andrew Huberman",
  "url": "https://hubermanlab.com",
  "platforms": {
    "spotify": "https://open.spotify.com/show/79CkJF3UJTHFV8Dse3Oy0P",
    "apple": "https://podcasts.apple.com/us/podcast/huberman-lab/id1545953110",
    "youtube": "https://www.youtube.com/@hubermanlab"
  },
  "features": [
    "Science-backed health protocols",
    "In-depth neuroscience explanations",
    "Practical daily routines",
    "Expert guest interviews",
    "Free educational content"
  ],
  "pros": [
    "Extremely detailed and evidence-based",
    "Actionable health advice",
    "Excellent communicator"
  ],
  "cons": [
    "Episodes are very long (2-3 hours)",
    "Can be overwhelming with detail",
    "Sometimes too technical"
  ],
  "rating": 4.9,
  "episodeCount": 190,
  "frequency": "Weekly",
  "averageDuration": "120 minutes",
  "firstEpisode": "2021-01-01",
  "lastUpdated": "2026-02-24",
  "tags": [
    "health",
    "science",
    "neuroscience",
    "wellness",
    "education"
  ]
}